adwords_reports/__init__.py
adwords_reports/account.py
adwords_reports/account_label.py
adwords_reports/client.py
adwords_reports/micro_amounts.py
adwords_reports/report_definition.py
adwords_reports-1.2.2.dist-info/DESCRIPTION.rst
adwords_reports-1.2.2.dist-info/METADATA
adwords_reports-1.2.2.dist-info/RECORD
adwords_reports-1.2.2.dist-info/WHEEL
adwords_reports-1.2.2.dist-info/metadata.json
adwords_reports-1.2.2.dist-info/top_level.txt
