Metadata-Version: 2.0
Name: adwords-reports
Version: 1.2.2
Summary: Pythonic wrapper of the Google AdWords API for easy reporting.
Home-page: https://github.com/SaturnFromTitan/adwords_reports
Author: Martin Winkel
Author-email: martin.winkel.pps@gmail.com
License: Apache License 2.0
Keywords: data analytics api wrapper google adwords reports reporting
Platform: UNKNOWN
Classifier: Intended Audience :: Developers
Classifier: Programming Language :: Python :: 2.7
Classifier: Programming Language :: Python :: 3.5
Classifier: Programming Language :: Python :: 3.6
Requires-Dist: googleads
Requires-Dist: pandas
Requires-Dist: retrying
